blindai_preview/Intel_SGX_Provisioning_Certification_RootCA.pem
blindai_preview/__init__.py
blindai_preview/_dcap_attestation.py
blindai_preview/client.py
blindai_preview/manifest.toml
blindai_preview/testing.py
blindai_preview/utils.py
blindai_preview-0.0.8.dist-info/METADATA
blindai_preview-0.0.8.dist-info/WHEEL
blindai_preview-0.0.8.dist-info/RECORD
